eyeball/__init__.py
eyeball/analyzer.py
eyeball/cli.py
eyeball/config.py
eyeball/harness.py
eyeball/inspector.py
eyeball/introspect.py
eyeball/resolver.py
eyeball/runner.py
eyeball/tester.py
jaymd96_eyeball-0.1.0.dist-info/METADATA
jaymd96_eyeball-0.1.0.dist-info/WHEEL
jaymd96_eyeball-0.1.0.dist-info/entry_points.txt
jaymd96_eyeball-0.1.0.dist-info/RECORD
