Metadata-Version: 2.4
Name: jaymd96-eyeball
Version: 0.1.0
Summary: Code introspection CLI for LLM-assisted development with structured JSON output
Project-URL: Homepage, https://github.com/jaymd96/eyeball
Project-URL: Documentation, https://github.com/jaymd96/eyeball#readme
Project-URL: Repository, https://github.com/jaymd96/eyeball
Author-email: James <jaymd96@users.noreply.github.com>
License-Expression: MIT
Keywords: cli,development,introspection,llm,probes,testing,verification
Classifier: Development Status :: 4 - Beta
Classifier: Environment :: Console
Classifier: Intended Audience :: Developers
Classifier: License :: OSI Approved :: MIT License
Classifier: Operating System :: OS Independent
Classifier: Programming Language :: Python :: 3
Classifier: Programming Language :: Python :: 3.10
Classifier: Programming Language :: Python :: 3.11
Classifier: Programming Language :: Python :: 3.12
Classifier: Topic :: Software Development :: Libraries :: Python Modules
Classifier: Topic :: Software Development :: Testing
Requires-Python: >=3.10
Requires-Dist: click>=8.0
Provides-Extra: dev
Requires-Dist: pytest-cov>=4.0; extra == 'dev'
Requires-Dist: pytest-json-report>=1.5; extra == 'dev'
Requires-Dist: pytest>=7.0; extra == 'dev'
Provides-Extra: toml
Requires-Dist: tomli>=2.0; (python_version < '3.11') and extra == 'toml'
